cudaq_qec/__init__.py
cudaq_qec/_pycudaqx_qec_the_suffix_matters_cudaq_qec.cpython-311-aarch64-linux-gnu.so
cudaq_qec/patch.py
cudaq_qec/lib/libcudaq-qec.so
cudaq_qec/lib/decoder-plugins/libcudaq-qec-example.so
cudaq_qec/lib/decoder-plugins/libcudaq-qec-nv-qldpc-decoder.so
cudaq_qec/plugins/codes/example.py
cudaq_qec/plugins/decoders/__init__.py
cudaq_qec/plugins/decoders/example.py
cudaq_qec/plugins/decoders/tensor_network_decoder.py
cudaq_qec/plugins/decoders/tensor_network_utils/__init__.py
cudaq_qec/plugins/decoders/tensor_network_utils/contractors.py
cudaq_qec/plugins/decoders/tensor_network_utils/noise_models.py
cudaq_qec/plugins/decoders/tensor_network_utils/tensor_network_factory.py
cudaq_qec-0.4.0.post1.dist-info/METADATA
cudaq_qec-0.4.0.post1.dist-info/WHEEL
cudaq_qec-0.4.0.post1.dist-info/RECORD
