Metadata-Version: 2.2
Name: cudaq-qec
Version: 0.4.0.post1
Summary: Accelerated libraries for Quantum Error Correction built on CUDA-Q
Author: NVIDIA Corporation & Affiliates
Maintainer: NVIDIA Corporation & Affiliates
Classifier: Intended Audience :: Science/Research
Classifier: Intended Audience :: Developers
Classifier: Programming Language :: Python
Classifier: Programming Language :: Python :: 3
Classifier: Programming Language :: Python :: 3.10
Classifier: Programming Language :: Python :: 3.11
Classifier: Programming Language :: Python :: 3.12
Classifier: Programming Language :: Python :: 3.13
Classifier: Environment :: GPU :: NVIDIA CUDA
Classifier: Environment :: GPU :: NVIDIA CUDA :: 12
Classifier: Topic :: Software Development
Classifier: Topic :: Scientific/Engineering
Project-URL: Homepage, https://nvidia.github.io/cudaqx
Project-URL: Documentation, https://nvidia.github.io/cudaqx/components/qec/introduction.html
Project-URL: Repository, https://github.com/NVIDIA/cudaqx
Requires-Python: >=3.10
Requires-Dist: cuda-quantum-cu12>=0.12
Provides-Extra: tensor-network-decoder
Requires-Dist: quimb; extra == "tensor-network-decoder"
Requires-Dist: opt_einsum; extra == "tensor-network-decoder"
Requires-Dist: torch; extra == "tensor-network-decoder"
Requires-Dist: cuquantum-python-cu12~=25.06; extra == "tensor-network-decoder"
